kisa_seed_cbc
