Metadata-Version: 1.0
Name: seed128cbc
Version: 0.0.4
Summary: SEED128_CBC TYPE ENCRYPTION & DECRYPTION
Home-page: UNKNOWN
Author: Yoonseok
Author-email: ys12247@gmail.com
License: MIT
Platform: UNKNOWN
